huzzer/__init__.py
huzzer/__main__.py
huzzer/code_gen.py
huzzer/expressions.py
huzzer/function_generator.py
huzzer/huzz.py
huzzer/version.py
huzzer/namers/__init__.py
huzzer/namers/default_namer.py
huzzer/tokenizing/SubHaskellLexer.py
huzzer/tokenizing/SubHaskellListener.py
huzzer/tokenizing/SubHaskellParser.py
huzzer/tokenizing/SubHaskellVisitor.py
huzzer/tokenizing/__init__.py
huzzer/tokenizing/tokenize.py
huzzer-0.1.2.dist-info/DESCRIPTION.rst
huzzer-0.1.2.dist-info/METADATA
huzzer-0.1.2.dist-info/RECORD
huzzer-0.1.2.dist-info/WHEEL
huzzer-0.1.2.dist-info/entry_points.txt
huzzer-0.1.2.dist-info/metadata.json
huzzer-0.1.2.dist-info/top_level.txt
