Metadata-Version: 2.0
Name: huzzer
Version: 0.1.2
Summary: A very-simple-subset-of-haskell fuzzer
Home-page: https://github.com/coopie/huzzer
Author: Sam Coope
Author-email: sam.j.coope@gmail.com
License: MIT
Keywords: haskell fuzzer generator
Platform: UNKNOWN
Classifier: Intended Audience :: Developers
Classifier: Natural Language :: English
Classifier: Operating System :: OS Independent
Classifier: Programming Language :: Python :: 3
Requires-Dist: docopt
Requires-Dist: antlr4-python3-runtime (==4.6)
